flask_lambda2/__init__.py
flask_lambda2-2.0.0.dist-info/DESCRIPTION.rst
flask_lambda2-2.0.0.dist-info/METADATA
flask_lambda2-2.0.0.dist-info/RECORD
flask_lambda2-2.0.0.dist-info/WHEEL
flask_lambda2-2.0.0.dist-info/metadata.json
flask_lambda2-2.0.0.dist-info/top_level.txt
