Metadata-Version: 2.0
Name: flask-lambda2
Version: 2.0.0
Summary: Python package to add compatibility between Flask and AWS Lambda for creating RESTful applications.
Home-page: https://github.com/seanpianka/flask-lambda2
Author: Sean Pianka
Author-email: pianka@eml.cc
License: MIT
Keywords: flask lambda aws api rest restful layer compatiblity endpoint
Platform: UNKNOWN
Classifier: Development Status :: 5 - Production/Stable
Classifier: Intended Audience :: Developers
Classifier: Topic :: Software Development :: Build Tools
Classifier: License :: OSI Approved :: MIT License
Classifier: Programming Language :: Python :: 2
Classifier: Programming Language :: Python :: 2.6
Classifier: Programming Language :: Python :: 2.7
Classifier: Programming Language :: Python :: 3
Classifier: Programming Language :: Python :: 3.2
Classifier: Programming Language :: Python :: 3.3
Classifier: Programming Language :: Python :: 3.4
Classifier: Programming Language :: Python :: 3.5
Classifier: Programming Language :: Python :: 3.6
